goslideapi/__init__.py
goslideapi/goslideapi.py
goslide_api_fork-0.3.0.dist-info/LICENSE
goslide_api_fork-0.3.0.dist-info/METADATA
goslide_api_fork-0.3.0.dist-info/WHEEL
goslide_api_fork-0.3.0.dist-info/top_level.txt
goslide_api_fork-0.3.0.dist-info/RECORD
