Metadata-Version: 2.1
Name: goslide-api-fork
Version: 0.3.0
Summary: Python API to utilise the goslide.io Open Cloud API
Home-page: https://github.com/zbessarab/goslide-api
Author: Alexander Kuiper
Author-email: ualex73@gmail.com
License: Apache License 2.0
Platform: UNKNOWN
Classifier: Programming Language :: Python :: 3
Classifier: License :: OSI Approved :: Apache Software License
Classifier: Operating System :: OS Independent
Requires-Dist: aiohttp
Requires-Dist: asyncio
